{
  "team": "hokkaido-team2",
  "investigatedAt": "2026-07-15",
  "facilities": [
    {
      "verdict": "include",
      "name": "北きつね牧場",
      "kana": "きたきつねぼくじょう",
      "pref": "北海道",
      "city": "北見市",
      "type": "zoo",
      "lat": 43.7776,
      "lng": 143.5094,
      "url": "https://kitakitsune-farm.com/",
      "sourceUrls": ["https://kitakitsune-farm.com/", "https://kitamikanko.jp/spot/157/"],
      "status": "open",
      "lastVerifiedAt": "2026-07-15",
      "proposedId": "hokkaido_kitakitsune_farm",
      "coordSource": "公式サイト記載の住所『北海道北見市留辺蘂町花丘52-1』の字レベル（北海道北見市留辺蘂町花丘）を国土地理院ジオコーディングAPIで変換（43.7776, 143.5094）。番地までは索引になし。",
      "adoptionBasis": "キタキツネ・エゾタヌキを放し飼いで展示する常設の観光牧場で、動物展示（観覧・エサやり）が来園目的の中心。包含基準の『牧場・ふれあい施設は動物展示が主要な来場目的なら含める』に合致。のぼりべつクマ牧場等の同種施設の分類前例（type: zoo）に準拠。",
      "note": "年中無休。夏季（5〜10月末）9:00〜17:00、冬季（11〜4月末）9:00〜16:00。公式サイトに閉園・休園の告知なし。"
    },
    {
      "verdict": "include",
      "name": "幌延町トナカイ観光牧場",
      "kana": "ほろのべちょうとなかいかんこうぼくじょう",
      "pref": "北海道",
      "city": "天塩郡幌延町",
      "type": "zoo",
      "lat": 45.0571,
      "lng": 141.8997,
      "url": "http://www.tonakai-farm.com/",
      "sourceUrls": [
        "https://www.town.horonobe.lg.jp/www4/section/sangyo/le009f00000017ha.html",
        "https://www.visit-hokkaido.jp/spot/detail_10397.html"
      ],
      "status": "open",
      "lastVerifiedAt": "2026-07-15",
      "proposedId": "hokkaido_horonobe_reindeer_farm",
      "coordSource": "幌延町公式サイト記載の住所『北海道天塩郡幌延町字北進398番地1』の字レベル（北海道幌延町北進）を国土地理院ジオコーディングAPIで変換（45.0571, 141.8997）。",
      "adoptionBasis": "フィンランド由来のトナカイ約30頭を飼育・展示し、エサやり体験やそりツアーも行う幌延町運営（産業建設課所管）の常設観光牧場。動物展示が来園目的の中心のため包含基準に合致。",
      "note": "入場無料（エサやり等は有料）。休業日は毎週月・火曜日、年末年始。公式サイト（www.tonakai-farm.com）はSSL証明書エラーがあり自動取得ツールでは閲覧不能だったため、幌延町公式ページを一次情報として採用。2026年7月時点で閉鎖・休業の情報は確認されず。"
    },
    {
      "verdict": "include",
      "name": "稚内市動物ふれあいランド",
      "kana": "わっかないしどうぶつふれあいらんど",
      "pref": "北海道",
      "city": "稚内市",
      "type": "other",
      "lat": 45.2998,
      "lng": 141.8349,
      "url": "https://w-shinko.co.jp/animalland/",
      "sourceUrls": ["https://w-shinko.co.jp/animalland/", "https://www.city.wakkanai.hokkaido.jp/kanko/midokoro/spot/doubutsufureai.html"],
      "status": "open",
      "lastVerifiedAt": "2026-07-15",
      "proposedId": "hokkaido_wakkanai_animal_fureai_land",
      "coordSource": "公式サイト記載の住所『稚内市声問村字恵北』の字レベル（北海道稚内市声問村）を国土地理院ジオコーディングAPIで変換（45.2998, 141.8349）。番地までは索引になし。",
      "adoptionBasis": "ヤギ・ウサギ・ポニー・七面鳥等のミニ動物園と、映画『南極物語』出演犬タロ・ジロゆかりの『スター犬の里』を核とする常設施設で、稚内振興公社（第三セクター）が運営。約6,000平米のドッグランとゲストハウスを併設するが、公式に『動物ふれあいランド』を自認し集客の中心は動物とのふれあいであるため、包含基準の牧場・ふれあい施設要件に合致。分類は先例（『ふれあい施設』自認＝other）に準拠。",
      "note": "季節営業。開園期間は4月29日〜9月30日、営業時間は平日11:00〜16:00・土日祝10:00〜16:00、定休日は毎週月曜（祝日の場合は翌日）。調査時点（2026-07-15）は営業期間中。"
    },
    {
      "verdict": "include",
      "name": "鹿牧場",
      "kana": "しかぼくじょう",
      "pref": "北海道",
      "city": "紋別郡西興部村",
      "type": "zoo",
      "lat": 44.3442,
      "lng": 143.0045,
      "url": "https://www.vill.nishiokoppe.lg.jp/feeuub000001ul9d.html",
      "sourceUrls": ["https://www.vill.nishiokoppe.lg.jp/feeuub000001ul9d.html", "https://zoo.hokkaido.jp/nishiokoppe/"],
      "status": "open",
      "lastVerifiedAt": "2026-07-15",
      "proposedId": "hokkaido_nishiokoppe_deer_farm",
      "coordSource": "西興部村公式サイト記載の住所『北海道紋別郡西興部村字中藻』の字レベル（北海道西興部村中藻）を国土地理院ジオコーディングAPIで変換（44.3442, 143.0045）。番地は未公表。",
      "adoptionBasis": "約7haの牧草地を高さ2〜3mのフェンスで囲い、エゾシカ約30頭を飼育・公開する常設の観光牧場（西興部村養鹿研究会が運営）。入場無料でエサ（有料）を通じた至近距離での観覧が来訪目的の中心のため、包含基準の牧場・ふれあい施設要件に合致。",
      "note": "通年営業、9:00〜17:00、年中無休（一部情報源）。公式の施設名は単に『鹿牧場』（『鹿牧場公園』表記の二次情報サイトあり）。閉鎖・休止の情報は確認されず。西興部村役場公式ページでは営業時間・休業日・料金が明記されておらず、これらは観光サイト情報に基づく（未確認情報として扱う）。"
    },
    {
      "verdict": "include",
      "name": "オホーツクシマリス公園",
      "kana": "おほーつくしまりすこうえん",
      "pref": "北海道",
      "city": "網走市",
      "type": "zoo",
      "lat": 43.9651,
      "lng": 144.2057,
      "url": "https://visit-abashiri.jp/en/culture/bd619c302fe51d484ff522c824a63fb6510c0386.html",
      "sourceUrls": ["https://eastern-hokkaido-style.jp/archives/01677/", "https://visit-abashiri.jp/en/culture/bd619c302fe51d484ff522c824a63fb6510c0386.html"],
      "status": "open",
      "lastVerifiedAt": "2026-07-15",
      "proposedId": "hokkaido_okhotsk_chipmunk_park",
      "coordSource": "観光サイト記載の住所『北海道網走市呼人352』の字レベル（北海道網走市呼人）を国土地理院ジオコーディングAPIで変換（43.9651, 144.2057）。番地までは索引になし。",
      "adoptionBasis": "手乗りエサやり体験ができる半放し飼いのエゾシマリス約40頭を展示する常設施設で、動物展示（エサやり体験）が来園目的の中心のため包含基準に合致。公式運営者名は情報源に明記なし。",
      "note": "季節営業。営業期間は例年5月上旬〜10月中旬（シマリスの活動状況により変動）、営業時間10:00〜16:00（最終受付15:30）、定休日は火・水曜日、冬期（10月中旬〜4月下旬）は休園。2021年に敷地内カフェ含む事業譲渡の公募情報が見られたが、2026年時点の複数の観光サイトで通常の営業時間・料金が案内されており、営業継続を確認。調査時点（2026-07-15）はシーズン中。"
    }
  ]
}
